pytiers/__init__.py
pytiers/by.py
pytiers/core.py
pytiers/parameters.py
pytiers/utils.py
pytiers-2.1.15.dist-info/METADATA
pytiers-2.1.15.dist-info/WHEEL
pytiers-2.1.15.dist-info/top_level.txt
pytiers-2.1.15.dist-info/RECORD
