Metadata-Version: 2.1
Name: pytiers
Version: 2.1.15
Author: Huang Bo-Xuan
Author-email: r09142003@gmail.com
Requires-Dist: seaborn
Requires-Dist: matplotlib
Requires-Dist: pandas
Requires-Dist: plotly
Requires-Dist: nbformat (>=4.2.0)
Requires-Dist: numpy
